.gitattributes
.gitignore
README.md
requirements.txt
setup.py
.github/workflows/release.yml
scrapinglib/__init__.py
scrapinglib/airav.py
scrapinglib/api.py
scrapinglib/avsox.py
scrapinglib/carib.py
scrapinglib/dlsite.py
scrapinglib/fanza.py
scrapinglib/fc2.py
scrapinglib/gcolle.py
scrapinglib/getchu.py
scrapinglib/httprequest.py
scrapinglib/imdb.py
scrapinglib/jav321.py
scrapinglib/javbus.py
scrapinglib/javday.py
scrapinglib/javdb.py
scrapinglib/javlibrary.py
scrapinglib/madouclub.py
scrapinglib/madouqu.py
scrapinglib/mgstage.py
scrapinglib/parser.py
scrapinglib/storyline.py
scrapinglib/tmdb.py
scrapinglib/utils.py
scrapinglib/xcity.py
scrapinglib.egg-info/PKG-INFO
scrapinglib.egg-info/SOURCES.txt
scrapinglib.egg-info/dependency_links.txt
scrapinglib.egg-info/requires.txt
scrapinglib.egg-info/top_level.txt
tests/test.py