Metadata-Version: 2.4
Name: scrapinglib
Version: 0.7.1
Home-page: https://github.com/Suwmlee/scrapinglib
Author: suwmlee
Author-email: suwmlee@gmail.com
Project-URL: Bug Tracker, https://github.com/Suwmlee/scrapinglib/issues
Project-URL: Source, https://github.com/Suwmlee/scrapinglib
Classifier: Programming Language :: Python :: 3
Requires-Python: >=3.7
Requires-Dist: lxml
Requires-Dist: pysocks
Requires-Dist: mechanicalsoup
Requires-Dist: cloudscraper
Dynamic: author
Dynamic: author-email
Dynamic: classifier
Dynamic: description
Dynamic: description-content-type
Dynamic: home-page
Dynamic: project-url
Dynamic: requires-dist
Dynamic: requires-python
